topologic_core.cpython-39-darwin.so
topologic_core.dylibs/libTKGeomAlgo.7.7.0.dylib
topologic_core.dylibs/libTKGeomBase.7.7.0.dylib
topologic_core.dylibs/libTKBRep.7.7.0.dylib
topologic_core.dylibs/libc++.1.0.dylib
topologic_core.dylibs/libTKOffset.7.7.0.dylib
topologic_core.dylibs/libTKPrim.7.7.0.dylib
topologic_core.dylibs/libTKBool.7.7.0.dylib
topologic_core.dylibs/libTKG3d.7.7.0.dylib
topologic_core.dylibs/libTKShHealing.7.7.0.dylib
topologic_core.dylibs/libTKMath.7.7.0.dylib
topologic_core.dylibs/libTKG2d.7.7.0.dylib
topologic_core.dylibs/libTKMesh.7.7.0.dylib
topologic_core.dylibs/libTKBO.7.7.0.dylib
topologic_core.dylibs/libTKernel.7.7.0.dylib
topologic_core.dylibs/libTKFillet.7.7.0.dylib
topologic_core.dylibs/libTKTopAlgo.7.7.0.dylib
topologic_core-8.0.1.dist-info/RECORD
topologic_core-8.0.1.dist-info/WHEEL
topologic_core-8.0.1.dist-info/top_level.txt
topologic_core-8.0.1.dist-info/METADATA
