Metadata-Version: 2.1
Name: topologic_core
Version: 8.0.1
Summary: TopologicPythonBindings wrapper package
Author: Topologic Authors
Author-email: wassim.jabi@gmail.com
Requires-Python: >=3.8
